merge_dataframes/__init__.py
merge_dataframes/merge_dataframes.py
merge_dataframes-0.1.1.dist-info/License.txt
merge_dataframes-0.1.1.dist-info/METADATA
merge_dataframes-0.1.1.dist-info/WHEEL
merge_dataframes-0.1.1.dist-info/top_level.txt
merge_dataframes-0.1.1.dist-info/RECORD
