Metadata-Version: 2.1
Name: merge_dataframes
Version: 0.1.1
Summary: A Python package to merge two Pandas DataFrames
Home-page: https://github.com/laxmankusuma/merge_dataframes
Author: Laxman Kusuma
Author-email: laxman.kusuma@gmail.com
Classifier: Programming Language :: Python :: 3
Classifier: License :: OSI Approved :: MIT License
Classifier: Operating System :: OS Independent
Requires-Python: >=3.6
License-File: License.txt
Requires-Dist: pandas>=1.0.0
